AutoPyPack/AutoPyPack.py
AutoPyPack/__init__.py
AutoPyPack/autopypack/__init__.py
AutoPyPack/autopypack/cli.py
AutoPyPack/autopypack/core.py
AutoPyPack/autopypack/magic.py
AutoPyPack/autopypack/mappings.json
autopypack-1.3.0.dist-info/METADATA
autopypack-1.3.0.dist-info/WHEEL
autopypack-1.3.0.dist-info/entry_points.txt
autopypack-1.3.0.dist-info/top_level.txt
autopypack-1.3.0.dist-info/RECORD
