Metadata-Version: 2.4
Name: autopypack
Version: 1.3.0
Summary: Automatically installs missing Python libraries when running your code.
Home-page: https://github.com/harshRaj1601/AutoPyPack
Author: Harsh Jaiswal
Author-email: Harsh Jaiswal <harshrajjaiswal16012003@gmail.com>
License: MIT
Project-URL: Homepage, https://github.com/harshRaj1601/AutoPyPack
Project-URL: Repository, https://github.com/harshRaj1601/AutoPyPack
Project-URL: Issues, https://github.com/harshRaj1601/AutoPyPack/issues
Classifier: Programming Language :: Python :: 3
Classifier: Programming Language :: Python :: 3.8
Classifier: Programming Language :: Python :: 3.9
Classifier: Programming Language :: Python :: 3.10
Classifier: Programming Language :: Python :: 3.11
Classifier: Programming Language :: Python :: 3.12
Classifier: License :: OSI Approved :: MIT License
Classifier: Operating System :: OS Independent
Classifier: Development Status :: 4 - Beta
Classifier: Intended Audience :: Developers
Classifier: Topic :: Software Development :: Libraries :: Python Modules
Requires-Python: >=3.8
Requires-Dist: ipython>=7.0.0
Requires-Dist: setuptools
Provides-Extra: dev
Requires-Dist: pytest>=7.0.0; extra == "dev"
Requires-Dist: pytest-cov>=4.0.0; extra == "dev"
Requires-Dist: mypy>=1.0.0; extra == "dev"
Requires-Dist: black>=23.0.0; extra == "dev"
Requires-Dist: ruff>=0.1.0; extra == "dev"
Dynamic: author
Dynamic: home-page
Dynamic: requires-python
